[
  {
    "success": true,
    "scoring_result": {
      "skills": {
        "raw_score": 85,
        "weight_given": 60,
        "normalized_percentage": 36.4,
        "weighted_contribution": 31.0
      },
      "experience": {
        "raw_score": 75,
        "weight_given": 60,
        "normalized_percentage": 36.4,
        "weighted_contribution": 27.3
      },
      "education": {
        "raw_score": 90,
        "weight_given": 15,
        "normalized_percentage": 9.1,
        "weighted_contribution": 8.19
      },
      "presentation": {
        "raw_score": 80,
        "weight_given": 10,
        "normalized_percentage": 6.1,
        "weighted_contribution": 4.88
      },
      "certifications": {
        "raw_score": 85,
        "weight_given": 5,
        "normalized_percentage": 3.0,
        "weighted_contribution": 2.55
      },
      "projects": {
        "raw_score": 75,
        "weight_given": 5,
        "normalized_percentage": 3.0,
        "weighted_contribution": 2.25
      },
      "soft_skills": {
        "raw_score": 70,
        "weight_given": 5,
        "normalized_percentage": 3.0,
        "weighted_contribution": 2.1
      },
      "industry_knowledge": {
        "raw_score": 65,
        "weight_given": 5,
        "normalized_percentage": 3.0,
        "weighted_contribution": 1.95
      },
      "total_score": 80.22,
      "metadata": {
        "resume_path": "documents/final5resume.pdf",
        "job_description_path": "documents/Bottomline_ Intern + FTE - JD 2026 Batch.pdf",
        "criteria_requirements": {
          "technical_skills": 60,
          "experience": 60,
          "education": 15,
          "presentation": 10,
          "certifications": 5,
          "projects": 5,
          "soft_skills": 5,
          "industry_knowledge": 5
        },
        "normalized_weights": {
          "technical_skills": 36.36363636363637,
          "experience": 36.36363636363637,
          "education": 9.090909090909092,
          "presentation": 6.0606060606060606,
          "certifications": 3.0303030303030303,
          "projects": 3.0303030303030303,
          "soft_skills": 3.0303030303030303,
          "industry_knowledge": 3.0303030303030303
        }
      },
      "gap_analysis": {
        "missing_skills": [
          ".NET",
          "Analytical skills",
          "Attention to detail",
          "BE/B.Tech – CSE/IT/IS",
          "Excellent communication skills",
          "HTML/CSS",
          "Java",
          "JavaScript",
          "Logical skills",
          "Positive attitude",
          "Python",
          "React",
          "SQL",
          "Self-learning",
          "Strong Aptitude"
        ],
        "experience_gap_years": 0.0,
        "education_gap": null
      }
    }
  },
  {
    "success": true,
    "scoring_result": {
      "skills": {
        "raw_score": 85,
        "weight_given": 60,
        "normalized_percentage": 36.4,
        "weighted_contribution": 30.94
      },
      "experience": {
        "raw_score": 75,
        "weight_given": 60,
        "normalized_percentage": 36.4,
        "weighted_contribution": 27.3
      },
      "education": {
        "raw_score": 90,
        "weight_given": 15,
        "normalized_percentage": 9.1,
        "weighted_contribution": 8.19
      },
      "presentation": {
        "raw_score": 70,
        "weight_given": 10,
        "normalized_percentage": 6.1,
        "weighted_contribution": 4.27
      },
      "certifications": {
        "raw_score": 0,
        "weight_given": 5,
        "normalized_percentage": 3.0,
        "weighted_contribution": 0.0
      },
      "projects": {
        "raw_score": 80,
        "weight_given": 5,
        "normalized_percentage": 3.0,
        "weighted_contribution": 2.4
      },
      "soft_skills": {
        "raw_score": 70,
        "weight_given": 5,
        "normalized_percentage": 3.0,
        "weighted_contribution": 2.1
      },
      "industry_knowledge": {
        "raw_score": 60,
        "weight_given": 5,
        "normalized_percentage": 3.0,
        "weighted_contribution": 1.8
      },
      "total_score": 76.9,
      "metadata": {
        "resume_path": "documents/Nirmit_Jain_Resume_Final.pdf",
        "job_description_path": "documents/Bottomline_ Intern + FTE - JD 2026 Batch.pdf",
        "criteria_requirements": {
          "technical_skills": 60,
          "experience": 60,
          "education": 15,
          "presentation": 10,
          "certifications": 5,
          "projects": 5,
          "soft_skills": 5,
          "industry_knowledge": 5
        },
        "normalized_weights": {
          "technical_skills": 36.36363636363637,
          "experience": 36.36363636363637,
          "education": 9.090909090909092,
          "presentation": 6.0606060606060606,
          "certifications": 3.0303030303030303,
          "projects": 3.0303030303030303,
          "soft_skills": 3.0303030303030303,
          "industry_knowledge": 3.0303030303030303
        }
      },
      "gap_analysis": {
        "missing_skills": [
          ".NET",
          "Analytical skills",
          "Attention to detail",
          "BE/B.Tech – CSE/IT/IS",
          "Excellent communication skills",
          "HTML/CSS",
          "Java",
          "JavaScript",
          "Logical skills",
          "Positive attitude",
          "Python",
          "React",
          "SQL",
          "Self-learning",
          "Strong Aptitude"
        ],
        "experience_gap_years": 0.0,
        "education_gap": null
      }
    }
  },
  {
    "success": true,
    "scoring_result": {
      "skills": {
        "raw_score": 75,
        "weight_given": 60,
        "normalized_percentage": 36.4,
        "weighted_contribution": 27.3
      },
      "experience": {
        "raw_score": 70,
        "weight_given": 60,
        "normalized_percentage": 36.4,
        "weighted_contribution": 25.48
      },
      "education": {
        "raw_score": 90,
        "weight_given": 15,
        "normalized_percentage": 9.1,
        "weighted_contribution": 8.19
      },
      "presentation": {
        "raw_score": 80,
        "weight_given": 10,
        "normalized_percentage": 6.1,
        "weighted_contribution": 4.88
      },
      "certifications": {
        "raw_score": 75,
        "weight_given": 5,
        "normalized_percentage": 3.0,
        "weighted_contribution": 2.25
      },
      "projects": {
        "raw_score": 70,
        "weight_given": 5,
        "normalized_percentage": 3.0,
        "weighted_contribution": 2.1
      },
      "soft_skills": {
        "raw_score": 70,
        "weight_given": 5,
        "normalized_percentage": 3.0,
        "weighted_contribution": 2.1
      },
      "industry_knowledge": {
        "raw_score": 50,
        "weight_given": 5,
        "normalized_percentage": 3.0,
        "weighted_contribution": 1.5
      },
      "total_score": 73.8,
      "metadata": {
        "resume_path": "documents/final4resume.pdf",
        "job_description_path": "documents/Bottomline_ Intern + FTE - JD 2026 Batch.pdf",
        "criteria_requirements": {
          "technical_skills": 60,
          "experience": 60,
          "education": 15,
          "presentation": 10,
          "certifications": 5,
          "projects": 5,
          "soft_skills": 5,
          "industry_knowledge": 5
        },
        "normalized_weights": {
          "technical_skills": 36.36363636363637,
          "experience": 36.36363636363637,
          "education": 9.090909090909092,
          "presentation": 6.0606060606060606,
          "certifications": 3.0303030303030303,
          "projects": 3.0303030303030303,
          "soft_skills": 3.0303030303030303,
          "industry_knowledge": 3.0303030303030303
        }
      },
      "gap_analysis": {
        "missing_skills": [
          ".NET",
          "Analytical skills",
          "Attention to detail",
          "BE/B.Tech – CSE/IT/IS",
          "Excellent communication skills",
          "HTML/CSS",
          "Java",
          "JavaScript",
          "Logical skills",
          "Positive attitude",
          "Python",
          "React",
          "SQL",
          "Self-learning",
          "Strong Aptitude"
        ],
        "experience_gap_years": 0.0,
        "education_gap": null
      }
    }
  }
]